<bug_report>
    <preconditions>Пользователь не залогинен в систему</preconditions>
    <STR>
        <step id="1">Открыть главную страницу</step>
        <step id="2">Выбрать тэг в разделе "Выберите, над чем хотели бы поработать"</step>
	<step id="3">Нажать на кнопку Подобрать психолога</step>
	<step id="4">Выбрать чек-бокс "С оплатой на сайте"</step>
	<step id="5">Нажать на кнопку Искать</step>
    </STR>
    <expected_result>Специалисты отображаются. Кнопка Все специалисты и количество специалистов отсутствует</expected_result>
    <actual_result>Под кнопкой Искать должна отображаться кнопка Все специалисты и рядом количество специалистов</actual_result>
</bug_report>
